attacut/__init__.py
attacut/dataloaders.py
attacut/evaluation.py
attacut/logger.py
attacut/minpythainlp.py
attacut/preprocessing.py
attacut/tokenizer.py
attacut/utils.py
attacut/version.py
attacut/artifacts/__init__.py
attacut/artifacts/__pycache__/__init__.cpython-37.pyc
attacut/artifacts/attacut-c/characters.json
attacut/artifacts/attacut-c/model.pth
attacut/artifacts/attacut-c/params.yml
attacut/artifacts/attacut-sc/characters.json
attacut/artifacts/attacut-sc/model.pth
attacut/artifacts/attacut-sc/params.yml
attacut/artifacts/attacut-sc/syllables.json
attacut/models/__init__.py
attacut/models/seq_ch_conv.py
attacut/models/seq_sy_ch_conv_concat.py
attacut-1.0.6.data/scripts/attacut-cli
attacut-1.0.6.dist-info/LICENSE
attacut-1.0.6.dist-info/METADATA
attacut-1.0.6.dist-info/WHEEL
attacut-1.0.6.dist-info/top_level.txt
attacut-1.0.6.dist-info/RECORD
