Metadata-Version: 2.1
Name: attacut
Version: 1.0.6
Summary: Fast and Reasonably Accurate Word Tokenizer for Thai
Home-page: https://github.com/PyThaiNLP/attacut
Author: Pattarawat Chormai et al.
Author-email: foomail@foo.com
License: UNKNOWN
Platform: UNKNOWN
Classifier: Natural Language :: Thai
Classifier: Programming Language :: Python :: 3
Classifier: License :: OSI Approved :: MIT License
Classifier: Operating System :: OS Independent
